setup.py
2or3.egg-info/PKG-INFO
2or3.egg-info/SOURCES.txt
2or3.egg-info/dependency_links.txt
2or3.egg-info/top_level.txt
lib2or3/__init__.py
scripts/2or3
scripts/ispy2
scripts/ispy3