Metadata-Version: 1.0
Name: 2or3
Version: 0.1.0
Summary: Writes a single byte to stdout (either "2" or "3") classifying a Python file using heuristics, giving priority to 3 if unclear
Home-page: https://github.com/thomasballinger/2or3
Author: Thomas Ballinger
Author-email: thomasballinger@gmail.com
License: MIT
Platform: UNKNOWN
